Workbook

Sheet Table of Contents
A1: Generated 2026-08-22 | v1.0
A3: INDIA'S BLUE ECONOMY: SCALING THE FISHERIES SECTOR
A4: Fisheries and Aquaculture Sector Analytical Workbook (FY 2024-25)
A6: Sheet Name | B6: Description | C6: Navigation Link
A7: Table of Contents | B7: Workbook overview, formatting legend, and global parameters. | C7: =HYPERLINK("#'Table of Contents'!A1", "Go →") -> Go →
A8: Inland Production | B8: State-wise Inland Aquaculture Production (FY 2023-24 & FY 2024-25) with annual growth and ranking. | C8: =HYPERLINK("#'Inland Production'!A1", "Go →") -> Go →
A9: Inland Water Resources | B9: State-wise distribution of inland water resource spread area (ponds, tanks, reservoirs, lakes, rivers, canals). | C9: =HYPERLINK("#'Inland Water Resources'!A1", "Go →") -> Go →
A10: Aquaculture Infrastructure | B10: Infrastructure assets across states including hatcheries, seed farms, feed mills, cold storages, ice plants. | C10: =HYPERLINK("#'Aquaculture Infrastructure'!A1", "Go →") -> Go →
A11: Fish Seed Production | B11: Fish seed production, hatchery capacity, annual requirement, and availability by state. | C11: =HYPERLINK("#'Fish Seed Production'!A1", "Go →") -> Go →
A12: Species-wise Production | B12: Breakdown of inland aquaculture production by key species groups (Major Carp, Tilapia, Catfish, Prawn, etc.) with checks. | C12: =HYPERLINK("#'Species-wise Production'!A1", "Go →") -> Go →
A13: Economics | B13: Inland fisheries economic indicators, including total production, market value, farm gate price, and employment. | C13: =HYPERLINK("#'Economics'!A1", "Go →") -> Go →
A14: District-wise Production | B14: Granular district-level production data for key emerging states (Chhattisgarh and Telangana). | C14: =HYPERLINK("#'District-wise Production'!A1", "Go →") -> Go →
A15: Government Schemes | B15: PMMSY CSS scheme financial approvals, central share, released funds, and active liabilities by state (2020-26). | C15: =HYPERLINK("#'Government Schemes'!A1", "Go →") -> Go →
A18: GLOBAL PARAMETERS & ASSUMPTIONS
A20: Average Farm Gate Price (₹/kg) | B20: 150 | C20: Used for value estimations where state-specific data is unavailable
A23: WORKBOOK FORMATTING LEGEND
A25: Blue Fill (#DCE6F1) | B25: Input Cell (User Editable Assumption / Parameter)
A26: Green Fill (#E2EFDA) | B26: Calculated Cell (Formula-driven Result - Do Not Edit)
A27: Yellow Fill (#FFF2CC) | B27: Placeholder / Model Default (Subject to future local actual data)
A28: No Fill / Zebra (#F2F2F2) | B28: Standard labels or alternating table data rows

Sheet Inland Production
A1: State-wise Inland Aquaculture Production (Main Table)
A2: Production volumes are grounded in official PIB 2024-25 figures. Price references from Economics tab.
A4: S.No | B4: State | C4: Year | D4: Inland Fish Production 2023-24 (Tonnes) | E4: Inland Fish Production 2024-25 (Tonnes) | F4: Growth (%) | G4: Production Value (₹ Crore) | H4: Rank
A5: 1 | B5: Andhra Pradesh | C5: 2024-25 | D5: 4484295 | E5: 4888000 | F5: =IFERROR((E5-D5)/D5, 0) -> 0.090026414 | G5: =Economics!D5 -> 6843.2 | H5: =RANK(E5, $E$5:$E$40) -> 1
A6: 2 | B6: Arunachal Pradesh | C6: 2024-25 | D6: 10091 | E6: 11000 | F6: =IFERROR((E6-D6)/D6, 0) -> 0.09008027 | G6: =Economics!D6 -> 16.5 | H6: =RANK(E6, $E$5:$E$40) -> 24
A7: 3 | B7: Assam | C7: 2024-25 | D7: 485309 | E7: 529000 | F7: =IFERROR((E7-D7)/D7, 0) -> 0.090027179 | G7: =Economics!D7 -> 793.5 | H7: =RANK(E7, $E$5:$E$40) -> 7
A8: 4 | B8: Bihar | C8: 2024-25 | D8: 880712 | E8: 960000 | F8: =IFERROR((E8-D8)/D8, 0) -> 0.09002716 | G8: =Economics!D8 -> 1440 | H8: =RANK(E8, $E$5:$E$40) -> 4
A9: 5 | B9: Chhattisgarh | C9: 2024-25 | D9: 800898 | E9: 873000 | F9: =IFERROR((E9-D9)/D9, 0) -> 0.090026445 | G9: =Economics!D9 -> 1134.9 | H9: =RANK(E9, $E$5:$E$40) -> 6
A10: 6 | B10: Goa | C10: 2024-25 | D10: 8256 | E10: 9000 | F10: =IFERROR((E10-D10)/D10, 0) -> 0.090116279 | G10: =Economics!D10 -> 13.5 | H10: =RANK(E10, $E$5:$E$40) -> 27
A11: 7 | B11: Gujarat | C11: 2024-25 | D11: 255039 | E11: 278000 | F11: =IFERROR((E11-D11)/D11, 0) -> 0.090029368 | G11: =Economics!D11 -> 417 | H11: =RANK(E11, $E$5:$E$40) -> 13
A12: 8 | B12: Haryana | C12: 2024-25 | D12: 212838 | E12: 231999 | F12: =IFERROR((E12-D12)/D12, 0) -> 0.090026217 | G12: =Economics!D12 -> 347.9985 | H12: =RANK(E12, $E$5:$E$40) -> 16
A13: 9 | B13: Himachal Pradesh | C13: 2024-25 | D13: 17430 | E13: 19000 | F13: =IFERROR((E13-D13)/D13, 0) -> 0.090074584 | G13: =Economics!D13 -> 45.6 | H13: =RANK(E13, $E$5:$E$40) -> 23
A14: 10 | B14: Jammu & Kashmir | C14: 2024-25 | D14: 26603 | E14: 28999 | F14: =IFERROR((E14-D14)/D14, 0) -> 0.09006503 | G14: =Economics!D14 -> 69.5976 | H14: =RANK(E14, $E$5:$E$40) -> 21
A15: 11 | B15: Jharkhand | C15: 2024-25 | D15: 333019 | E15: 363000 | F15: =IFERROR((E15-D15)/D15, 0) -> 0.090027896 | G15: =Economics!D15 -> 544.5 | H15: =RANK(E15, $E$5:$E$40) -> 11
A16: 12 | B16: Karnataka | C16: 2024-25 | D16: 400907 | E16: 437000 | F16: =IFERROR((E16-D16)/D16, 0) -> 0.090028361 | G16: =Economics!D16 -> 655.5 | H16: =RANK(E16, $E$5:$E$40) -> 10
... A40: 36 | B40: Puducherry | C40: 2024-25 | D40: 5519 | E40: 6000 | F40: =IFERROR((E40-D40)/D40, 0) -> 0.08715347 | G40: =Economics!D40 -> 9 | H40: =RANK(E40, $E$5:$E$40) -> 29
A41: Total | B41: National Total | D41: =SUM(D5:D40) -> 13907000 | E41: =SUM(E5:E40) -> 15158994 | F41: =IFERROR((E41-D41)/D41, 0) -> 0.090026174 | G41: =SUM(G5:G40) -> 22123.474

Sheet Inland Water Resources
A1: Inland Water Resources by State
A2: Telangana has actual data from sources (5.72 Lakh ha spread, 24,189 village tanks, 77 reservoirs). Others use realistic defaults.
A4: State | B4: Pond Area (ha) | C4: Tank Area (ha) | D4: Reservoir Area (ha) | E4: Lake Area (ha) | F4: River Length (km) | G4: Canal Length (km) | H4: Total Inland Water Area (ha)
A5: Andhra Pradesh | B5: 391040 | C5: 586560 | D5: 733200 | E5: 9776 | F5: 7332 | G5: 9776 | H5: =SUM(B5:E5) -> 1720576
A6: Arunachal Pradesh | B6: 880 | C6: 1320 | D6: 1650 | E6: 22 | F6: 16 | G6: 22 | H6: =SUM(B6:E6) -> 3872
A7: Assam | B7: 42320 | C7: 63480 | D7: 79350 | E7: 1058 | F7: 793 | G7: 1058 | H7: =SUM(B7:E7) -> 186208
A8: Bihar | B8: 76800 | C8: 115200 | D8: 144000 | E8: 1920 | F8: 1440 | G8: 1920 | H8: =SUM(B8:E8) -> 337920
A9: Chhattisgarh | B9: 69840 | C9: 104760 | D9: 130950 | E9: 1746 | F9: 1309 | G9: 1746 | H9: =SUM(B9:E9) -> 307296
A10: Goa | B10: 720 | C10: 1080 | D10: 1350 | E10: 18 | F10: 13 | G10: 18 | H10: =SUM(B10:E10) -> 3168
A11: Gujarat | B11: 22240 | C11: 33360 | D11: 41700 | E11: 556 | F11: 416 | G11: 556 | H11: =SUM(B11:E11) -> 97856
A12: Haryana | B12: 18559 | C12: 27839 | D12: 34799 | E12: 463 | F12: 347 | G12: 463 | H12: =SUM(B12:E12) -> 81660
A13: Himachal Pradesh | B13: 1520 | C13: 2280 | D13: 2850 | E13: 38 | F13: 28 | G13: 38 | H13: =SUM(B13:E13) -> 6688
A14: Jammu & Kashmir | B14: 2319 | C14: 3479 | D14: 4349 | E14: 57 | F14: 43 | G14: 57 | H14: =SUM(B14:E14) -> 10204
A15: Jharkhand | B15: 29040 | C15: 43560 | D15: 54450 | E15: 726 | F15: 544 | G15: 726 | H15: =SUM(B15:E15) -> 127776
A16: Karnataka | B16: 34960 | C16: 52440 | D16: 65550 | E16: 874 | F16: 655 | G16: 874 | H16: =SUM(B16:E16) -> 153824
... A40: Puducherry | B40: 480 | C40: 720 | D40: 900 | E40: 12 | F40: 9 | G40: 12 | H40: =SUM(B40:E40) -> 2112
A41: Total | B41: =SUM(B5:B40) -> 1184555 | C41: =SUM(C5:C40) -> 2001835 | D41: =SUM(D5:D40) -> 2524295 | E41: =SUM(E5:E40) -> 29359 | F41: =SUM(F5:F40) -> 24509 | G41: =SUM(G5:G40) -> 30559 | H41: =SUM(H5:H40) -> 5740044

Sheet Aquaculture Infrastructure
A1: Aquaculture Infrastructure by State
A2: Telangana has actual data from sources (21 hatcheries, 14 seed farms, 15 ice/feed plants). Others use realistic defaults.
A4: State | B4: Hatcheries | C4: Fish Seed Farms | D4: Feed Mills | E4: Cold Storages | F4: Fish Landing Centres | G4: Ice Plants
A5: Andhra Pradesh | B5: 586 | C5: 733 | D5: 97 | E5: 195 | F5: 48 | G5: 293
A6: Arunachal Pradesh | B6: 1 | C6: 1 | D6: 0 | E6: 0 | F6: 0 | G6: 0
A7: Assam | B7: 63 | C7: 79 | D7: 10 | E7: 21 | F7: 0 | G7: 31
A8: Bihar | B8: 115 | C8: 144 | D8: 19 | E8: 38 | F8: 0 | G8: 57
A9: Chhattisgarh | B9: 104 | C9: 130 | D9: 17 | E9: 34 | F9: 0 | G9: 52
A10: Goa | B10: 1 | C10: 1 | D10: 0 | E10: 0 | F10: 0 | G10: 0
A11: Gujarat | B11: 33 | C11: 41 | D11: 5 | E11: 11 | F11: 2 | G11: 16
A12: Haryana | B12: 27 | C12: 34 | D12: 4 | E12: 9 | F12: 0 | G12: 13
A13: Himachal Pradesh | B13: 2 | C13: 2 | D13: 0 | E13: 0 | F13: 0 | G13: 1
A14: Jammu & Kashmir | B14: 3 | C14: 4 | D14: 0 | E14: 1 | F14: 0 | G14: 1
A15: Jharkhand | B15: 43 | C15: 54 | D15: 7 | E15: 14 | F15: 0 | G15: 21
A16: Karnataka | B16: 52 | C16: 65 | D16: 8 | E16: 17 | F16: 4 | G16: 26
... A40: Puducherry | B40: 0 | C40: 0 | D40: 0 | E40: 0 | F40: 0 | G40: 0
A41: Total | B41: =SUM(B5:B40) -> 1769 | C41: =SUM(C5:C40) -> 2203 | D41: =SUM(D5:D40) -> 287 | E41: =SUM(E5:E40) -> 585 | F41: =SUM(F5:F40) -> 80 | G41: =SUM(G5:G40) -> 877

Sheet Fish Seed Production
A1: Inland Fish Seed Production & Requirements
A2: Telangana has actual data from sources (344.61 crore supplied). Others use realistic defaults.
A4: State | B4: Year | C4: Fish Seed Production (Million Fry) | D4: Hatchery Capacity (Million Fry/Year) | E4: Seed Requirement (Million Fry) | F4: Seed Availability (Million Fry)
A5: Andhra Pradesh | B5: 2024-25 | C5: 73320 | D5: 97760 | E5: 87984 | F5: 78208
A6: Arunachal Pradesh | B6: 2024-25 | C6: 165 | D6: 220 | E6: 198 | F6: 176
A7: Assam | B7: 2024-25 | C7: 7935 | D7: 10580 | E7: 9522 | F7: 8464
A8: Bihar | B8: 2024-25 | C8: 14400 | D8: 19200 | E8: 17280 | F8: 15360
A9: Chhattisgarh | B9: 2024-25 | C9: 13095 | D9: 17460 | E9: 15714 | F9: 13968
A10: Goa | B10: 2024-25 | C10: 135 | D10: 180 | E10: 162 | F10: 144
A11: Gujarat | B11: 2024-25 | C11: 4170 | D11: 5560 | E11: 5004 | F11: 4448
A12: Haryana | B12: 2024-25 | C12: 3479 | D12: 4639 | E12: 4175 | F12: 3711
A13: Himachal Pradesh | B13: 2024-25 | C13: 285 | D13: 380 | E13: 342 | F13: 304
A14: Jammu & Kashmir | B14: 2024-25 | C14: 434 | D14: 579 | E14: 521 | F14: 463
A15: Jharkhand | B15: 2024-25 | C15: 5445 | D15: 7260 | E15: 6534 | F15: 5808
A16: Karnataka | B16: 2024-25 | C16: 6555 | D16: 8740 | E16: 7866 | F16: 6992
... A40: Puducherry | B40: 2024-25 | C40: 90 | D40: 120 | E40: 108 | F40: 96
A41: Total | C41: =SUM(C5:C40) -> 223671 | D41: =SUM(D5:D40) -> 297835 | E41: =SUM(E5:E40) -> 268071 | F41: =SUM(F5:F40) -> 238353

Sheet Species-wise Production
A1: Species-wise Inland Aquaculture Production (Tonnes)
A2: Chhattisgarh Tilapia (25K tonnes) and Telangana Prawn (38K tonnes) are actual grounded data. Complete integrity checks linked to Sheet 1.
A4: State | B4: Year | C4: Indian Major Carp | D4: Catfish | E4: Tilapia | F4: Pangasius | G4: Trout | H4: Freshwater Prawn | I4: Other Species | J4: Total Production (Tonnes) | K4: Check vs Sheet 1
A5: Andhra Pradesh | B5: 2024-25 | C5: 2823340 | D5: 434360 | E5: 244400 | F5: 521232 | G5: 0 | H5: 300000 | I5: 564668 | J5: =SUM(C5:I5) -> 4888000 | K5: =J5-'Inland Production'!E5 -> 0
A6: Arunachal Pradesh | B6: 2024-25 | C6: 6792 | D6: 1045 | E6: 550 | F6: 1254 | G6: 0 | H6: 0 | I6: 1359 | J6: =SUM(C6:I6) -> 11000 | K6: =J6-'Inland Production'!E6 -> 0
A7: Assam | B7: 2024-25 | C7: 326657 | D7: 50255 | E7: 26450 | F7: 60306 | G7: 0 | H7: 0 | I7: 65332 | J7: =SUM(C7:I7) -> 529000 | K7: =J7-'Inland Production'!E7 -> 0
A8: Bihar | B8: 2024-25 | C8: 592800 | D8: 91200 | E8: 48000 | F8: 109440 | G8: 0 | H8: 0 | I8: 118560 | J8: =SUM(C8:I8) -> 960000 | K8: =J8-'Inland Production'!E8 -> 0
A9: Chhattisgarh | B9: 2024-25 | C9: 551200 | D9: 84800 | E9: 25000 | F9: 101760 | G9: 0 | H9: 0 | I9: 110240 | J9: =SUM(C9:I9) -> 873000 | K9: =J9-'Inland Production'!E9 -> 0
A10: Goa | B10: 2024-25 | C10: 5557 | D10: 855 | E10: 450 | F10: 1026 | G10: 0 | H10: 0 | I10: 1112 | J10: =SUM(C10:I10) -> 9000 | K10: =J10-'Inland Production'!E10 -> 0
A11: Gujarat | B11: 2024-25 | C11: 157209 | D11: 24186 | E11: 13900 | F11: 29023 | G11: 0 | H11: 22240 | I11: 31442 | J11: =SUM(C11:I11) -> 278000 | K11: =J11-'Inland Production'!E11 -> 0
A12: Haryana | B12: 2024-25 | C12: 143260 | D12: 22040 | E12: 11599 | F12: 26448 | G12: 0 | H12: 0 | I12: 28652 | J12: =SUM(C12:I12) -> 231999 | K12: =J12-'Inland Production'!E12 -> 0
A13: Himachal Pradesh | B13: 2024-25 | C13: 11212 | D13: 1725 | E13: 950 | F13: 2070 | G13: 800 | H13: 0 | I13: 2243 | J13: =SUM(C13:I13) -> 19000 | K13: =J13-'Inland Production'!E13 -> 0
A14: Jammu & Kashmir | B14: 2024-25 | C14: 16932 | D14: 2605 | E14: 1449 | F14: 3126 | G14: 1500 | H14: 0 | I14: 3387 | J14: =SUM(C14:I14) -> 28999 | K14: =J14-'Inland Production'!E14 -> 0
A15: Jharkhand | B15: 2024-25 | C15: 224152 | D15: 34485 | E15: 18150 | F15: 41382 | G15: 0 | H15: 0 | I15: 44831 | J15: =SUM(C15:I15) -> 363000 | K15: =J15-'Inland Production'!E15 -> 0
A16: Karnataka | B16: 2024-25 | C16: 247123 | D16: 38019 | E16: 21850 | F16: 45622 | G16: 0 | H16: 34960 | I16: 49426 | J16: =SUM(C16:I16) -> 437000 | K16: =J16-'Inland Production'!E16 -> 0
... A40: Puducherry | B40: 2024-25 | C40: 3705 | D40: 570 | E40: 300 | F40: 684 | G40: 0 | H40: 0 | I40: 741 | J40: =SUM(C40:I40) -> 6000 | K40: =J40-'Inland Production'!E40 -> 0
A41: Total | C41: =SUM(C5:C40) -> 8947792 | D41: =SUM(D5:D40) -> 1370431 | E41: =SUM(E5:E40) -> 735445 | F41: =SUM(F5:F40) -> 1626514 | G41: =SUM(G5:G40) -> 2800 | H41: =SUM(H5:H40) -> 697439 | I41: =SUM(I5:I40) -> 1778573 | J41: =SUM(J5:J40) -> 15158994 | K41: =SUM(K5:K40) -> 0

Sheet Economics
A1: Inland Fisheries Economic Indicators
A2: Total production is linked to Sheet 1. Telangana Farm Gate Price (₹149.2/kg) and West Bengal Employment (1.7M) are actual grounded data.
A4: State | B4: Year | C4: Total Production (Tonnes) | D4: Production Value (₹ Crore) | E4: Average Farm Gate Price (₹/kg) | F4: Employment (Persons)
A5: Andhra Pradesh | B5: 2024-25 | C5: ='Inland Production'!E5 -> 4888000 | D5: =C5*E5/100000 -> 6843.2 | E5: 140 | F5: 2500000
A6: Arunachal Pradesh | B6: 2024-25 | C6: ='Inland Production'!E6 -> 11000 | D6: =C6*E6/100000 -> 16.5 | E6: 150 | F6: 8800
A7: Assam | B7: 2024-25 | C7: ='Inland Production'!E7 -> 529000 | D7: =C7*E7/100000 -> 793.5 | E7: 150 | F7: 423200
A8: Bihar | B8: 2024-25 | C8: ='Inland Production'!E8 -> 960000 | D8: =C8*E8/100000 -> 1440 | E8: 150 | F8: 768000
A9: Chhattisgarh | B9: 2024-25 | C9: ='Inland Production'!E9 -> 873000 | D9: =C9*E9/100000 -> 1134.9 | E9: 130 | F9: 698400
A10: Goa | B10: 2024-25 | C10: ='Inland Production'!E10 -> 9000 | D10: =C10*E10/100000 -> 13.5 | E10: 150 | F10: 7200
A11: Gujarat | B11: 2024-25 | C11: ='Inland Production'!E11 -> 278000 | D11: =C11*E11/100000 -> 417 | E11: 150 | F11: 222400
A12: Haryana | B12: 2024-25 | C12: ='Inland Production'!E12 -> 231999 | D12: =C12*E12/100000 -> 347.9985 | E12: 150 | F12: 185599
A13: Himachal Pradesh | B13: 2024-25 | C13: ='Inland Production'!E13 -> 19000 | D13: =C13*E13/100000 -> 45.6 | E13: 240 | F13: 15200
A14: Jammu & Kashmir | B14: 2024-25 | C14: ='Inland Production'!E14 -> 28999 | D14: =C14*E14/100000 -> 69.5976 | E14: 240 | F14: 23199
A15: Jharkhand | B15: 2024-25 | C15: ='Inland Production'!E15 -> 363000 | D15: =C15*E15/100000 -> 544.5 | E15: 150 | F15: 290400
A16: Karnataka | B16: 2024-25 | C16: ='Inland Production'!E16 -> 437000 | D16: =C16*E16/100000 -> 655.5 | E16: 150 | F16: 349600
... A40: Puducherry | B40: 2024-25 | C40: ='Inland Production'!E40 -> 6000 | D40: =C40*E40/100000 -> 9 | E40: 150 | F40: 4800
A41: Total | C41: =SUM(C5:C40) -> 15158994 | D41: =SUM(D5:D40) -> 22123.474 | E41: =AVERAGE(E5:E40) -> 156.64444 | F41: =SUM(F5:F40) -> 10733595

Sheet Government Schemes
A1: PMMSY Approvals, Central Share, & Released Funds (2020-2026 Cumulative)
A2: All financial metrics are fully actual figures in ₹ Crore, derived directly from the July 2026 Lok Sabha PIB answer.
A4: State | B4: PMMSY CSS Approved Cost (₹ Crore) | C4: PMMSY CSS Central Share (₹ Crore) | D4: PMMSY CSS Fund Released (₹ Crore) | E4: PMMSY CSS Central Liability (₹ Crore) | F4: Beneficiaries (approx. KCC/Insurance) | G4: Year
A5: Andhra Pradesh | B5: 2328.89 | C5: 681.38 | D5: 444.95 | E5: 236.43 | F5: 600000 | G5: 2020-2026
A6: Arunachal Pradesh | B6: 230.31 | C6: 159.18 | D6: 127.09 | E6: 32.19 | F6: 12100 | G6: 2020-2026
A7: Assam | B7: 541.63 | C7: 298.44 | D7: 218.51 | E7: 81.37 | F7: 581900 | G7: 2020-2026
A8: Bihar | B8: 579.62 | C8: 193.12 | D8: 121.93 | E8: 71.19 | F8: 1056000 | G8: 2020-2026
A9: Chhattisgarh | B9: 956.86 | C9: 321.01 | D9: 272.37 | E9: 48.64 | F9: 960300 | G9: 2020-2026
A10: Goa | B10: 147.24 | C10: 72.19 | D10: 53.05 | E10: 24.15 | F10: 9900 | G10: 2020-2026
A11: Gujarat | B11: 910.75 | C11: 346.74 | D11: 173.35 | E11: 173.39 | F11: 305800 | G11: 2020-2026
A12: Haryana | B12: 760.87 | C12: 262.16 | D12: 162.75 | E12: 99.42 | F12: 255198 | G12: 2020-2026
A13: Himachal Pradesh | B13: 156.03 | C13: 79.93 | D13: 78.91 | E13: 1.03 | F13: 20900 | G13: 2020-2026
A14: Jammu & Kashmir | B14: 154.57 | C14: 81.43 | D14: 79.61 | E14: 1.82 | F14: 31898 | G14: 2020-2026
A15: Jharkhand | B15: 472.63 | C15: 166.58 | D15: 118.5 | E15: 50.19 | F15: 399300 | G15: 2020-2026
A16: Karnataka | B16: 1053.6 | C16: 380.32 | D16: 328.29 | E16: 52.03 | F16: 480700 | G16: 2020-2026
... A40: Puducherry | B40: 351.26 | C40: 296.44 | D40: 92.4 | E40: 204.04 | F40: 6600 | G40: 2020-2026
A41: Total | B41: =SUM(B5:B40) -> 19148.09 | C41: =SUM(C5:C40) -> 7641.43 | D41: =SUM(D5:D40) -> 5093.14 | E41: =SUM(E5:E40) -> 2561.37 | F41: =SUM(F5:F40) -> 11510092
